pyrestsdk/__init__.py
pyrestsdk/_abstract_service_client.py
pyrestsdk/_service_client.py
pyrestsdk/clientfactory/__init__.py
pyrestsdk/clientfactory/_abstract_client_factory.py
pyrestsdk/clientfactory/_http_client_factory.py
pyrestsdk/clientfactory/supports/__init__.py
pyrestsdk/clientfactory/supports/_supports_default_middleware.py
pyrestsdk/credential/__init__.py
pyrestsdk/credential/_abstract_basic_credential.py
pyrestsdk/credential/_abstract_credential.py
pyrestsdk/credential/_abstract_kerbrose_credential.py
pyrestsdk/credential/_abstract_token_credential.py
pyrestsdk/credential/_basic_credential.py
pyrestsdk/middleware/__init__.py
pyrestsdk/middleware/_base_authorization_handler.py
pyrestsdk/middleware/_base_middleware.py
pyrestsdk/middleware/_middleware_pipeline.py
pyrestsdk/middleware/_request_context.py
pyrestsdk/middleware/authorizationhandler/__init__.py
pyrestsdk/middleware/authorizationhandler/_authorization_handler.py
pyrestsdk/middleware/authorizationhandler/_basic_authorization_handler.py
pyrestsdk/middleware/authorizationhandler/_kerbose_authorization_handler.py
pyrestsdk/middleware/authorizationhandler/_token_authorization_handler.py
pyrestsdk/request/__init__.py
pyrestsdk/request/_abstract_request.py
pyrestsdk/request/_base_request310.py
pyrestsdk/request/_base_request39.py
pyrestsdk/request/_request.py
pyrestsdk/request/supports_types/__init__.py
pyrestsdk/request/supports_types/_supports_base_invoke_request.py
pyrestsdk/request/supports_types/_supports_generic_type.py
pyrestsdk/request/supports_types/_supports_header_options.py
pyrestsdk/request/supports_types/_supports_invoke_collection_request.py
pyrestsdk/request/supports_types/_supports_invoke_request.py
pyrestsdk/request/supports_types/_supports_query_options.py
pyrestsdk/request/supports_types/_supports_types.py
pyrestsdk/request/supports_types/methods/__init__.py
pyrestsdk/request/supports_types/methods/_supports_delete_method.py
pyrestsdk-0.6.0.dist-info/LICENSE
pyrestsdk-0.6.0.dist-info/METADATA
pyrestsdk-0.6.0.dist-info/WHEEL
pyrestsdk-0.6.0.dist-info/RECORD
