Metadata-Version: 2.1
Name: pyrestsdk
Version: 0.6.0
Summary: a toolkit to make writing SDKs in python simple
Author: Michael Canady
Requires-Python: >=3.8,<4.0
Classifier: Programming Language :: Python :: 3
Classifier: Programming Language :: Python :: 3.8
Classifier: Programming Language :: Python :: 3.9
Classifier: Programming Language :: Python :: 3.10
Classifier: Programming Language :: Python :: 3.11
Requires-Dist: StrEnum (>=0.4.10,<0.5.0)
Requires-Dist: requests (>=2.28.2,<3.0.0)
Requires-Dist: requests-kerberos (>=0.14.0,<0.15.0)
Requires-Dist: sphinx-autoapi (>=2.1.0,<3.0.0)
